deployConfig.py
deployHelpers.py
hesdeploy.py
lifecycle.py
hesdeploy-0.9.2.dist-info/DESCRIPTION.rst
hesdeploy-0.9.2.dist-info/METADATA
hesdeploy-0.9.2.dist-info/RECORD
hesdeploy-0.9.2.dist-info/WHEEL
hesdeploy-0.9.2.dist-info/entry_points.txt
hesdeploy-0.9.2.dist-info/metadata.json
hesdeploy-0.9.2.dist-info/top_level.txt
