Metadata-Version: 2.0
Name: hesdeploy
Version: 0.9.2
Summary: Hesburgh Libraries Deployment script
Home-page: https://github.com/ndlib/hesburgh_utilities/tree/master/scripts
Author: Harrison Beachey
Author-email: hbeachey@nd.edu
License: Apache Software License
Keywords: Deployment AWS
Platform: UNKNOWN
Classifier: Development Status :: 4 - Beta
Classifier: Intended Audience :: Developers
Classifier: Topic :: Software Development :: Libraries :: Python Modules
Classifier: License :: OSI Approved :: Apache Software License
Classifier: Programming Language :: Python :: 2.7
Requires-Dist: boto3
Requires-Dist: hesburgh-utilities (>=1.0.8)
Requires-Dist: PyYAML
